configcronos/__init__.py
configcronos/core/__init__.py
configcronos/core/entities/__init__.py
configcronos/core/entities/client.py
configcronos/core/entities/database.py
configcronos/core/entities/oracle.py
configcronos/core/entities/phase1.py
configcronos/core/entities/phase2.py
configcronos/core/entities/phase3.py
configcronos/core/entities/pinger.py
configcronos/core/entities/schedule.py
configcronos/core/entities/segment.py
configcronos/core/entities/sqls.py
configcronos/core/errors/__init__.py
configcronos/core/errors/no_connection.py
configcronos/core/errors/no_data_found.py
configcronos/core/repositories/__init__.py
configcronos/core/repositories/client_repository.py
configcronos/core/repositories/database_repository.py
configcronos/core/repositories/phase1_repository.py
configcronos/core/repositories/phase2_repository.py
configcronos/core/repositories/phase3_repository.py
configcronos/core/repositories/pinger_repository.py
configcronos/core/repositories/schedule_repository.py
configcronos/core/repositories/segment_repository.py
configcronos/core/repositories/sqls_repository.py
configcronos/core/usecases/__init__.py
configcronos/core/usecases/client.py
configcronos/core/usecases/database.py
configcronos/core/usecases/phase1.py
configcronos/core/usecases/phase2.py
configcronos/core/usecases/phase3.py
configcronos/core/usecases/pinger.py
configcronos/core/usecases/schedule.py
configcronos/core/usecases/segment.py
configcronos/core/usecases/sqls.py
configcronos/infra/__init__.py
configcronos/infra/api.py
configcronos/infra/configs/__init__.py
configcronos/infra/configs/configs.py
configcronos/infra/repositories/__init__.py
configcronos/infra/repositories/auth_repository.py
configcronos/infra/repositories/client_repository.py
configcronos/infra/repositories/database_repository.py
configcronos/infra/repositories/phase1_repository.py
configcronos/infra/repositories/phase2_repository.py
configcronos/infra/repositories/phase3_repository.py
configcronos-0.0.11.dist-info/METADATA
configcronos-0.0.11.dist-info/WHEEL
configcronos-0.0.11.dist-info/RECORD
