Metadata-Version: 2.1
Name: configcronos
Version: 0.0.11
Summary: ConfigCronos is a tool to manage configuration files for multiple servers.
Requires-Python: >=3.10
Requires-Dist: python-dotenv
Requires-Dist: requests
